spi_master.v
/*
Basado en el codigo del profesor Ferney, con unas modificaciones para que los bits los envie en el flanco de subida
Modulo:	SPI_ master 
Autor: 	ferney alberto beltran 
Curso: 	Digital 1
Año:	 	2024

Descripción:

                     _______________
                    |               |
           clk -----|               |
           rst -----|               |
 data_in [7:0] -----|               |---- sclk
         start -----|               |---- mosi
freq_div[15:0] -----|               |---- miso
data_out [7:0] <----|               |---- cs
          busy <----|               |
         avail <----|               |
                    |_______________|

CLK: 		Entrada del reloj del sistema.
RST: 		Señal de reset que inicializa el módulo.

CLOCK_DIV: Valor para configurar la velocidad de la comunicación SPI.

DATA_IN:  Datos que se van a transmitir al esclavo SPI.
DATA_OUT: Datos recibidos del esclavo.

START: 	Señal que inicia la transmisión de datos.
BUSY: 	Señal que indica si el módulo está ocupado en una transmisión.
AVAIL: 	Señal que indica que se ha recibido un dato completo.

MISO: 	Salida del Maestro, Entrada del Esclavo (Master In Slave Out).
MOSI: 	Entrada del Maestro, Salida del Esclavo (Master Out Slave In).
SCLK: 	Señal de reloj SPI que sincroniza la transmisión de datos.
CS: 		Chip Select, activa o desactiva el esclavo seleccionado.

*/

module spi_master(
   input clk,                // Reloj del sistema
   input reset,              // Señal de reset
   input [7:0] data_in,      // Datos de entrada para enviar
   input start,              // Inicio de la transmisión
   input [15:0] div_factor,   // Divisor del reloj para la velocidad SPI
   input  miso,         // Master In Slave Out
   output reg mosi,               // Master Out Slave In
   output reg sclk,          // Reloj SPI
   output reg cs,            // Chip Select
   output reg [7:0] data_out, // Datos recibidos
   output reg busy,          // Señal de ocupado
   output reg avail  // Señal de dato recibido
);

	reg [7:0] shift_reg;     // Registro de desplazamiento para enviar/recibir datos
   reg [3:0] bit_count;     // Contador de bits transmitidos
   reg [15:0] clk_count;    // Contador del reloj para generar sclk
   reg active;              // Señal interna que indica si la transmisión está activa
	reg p;
   
	

	always @(posedge clk or posedge reset) begin
	  if (reset) begin
			sclk <= 0;
			cs <= 1;
			shift_reg <= 0;
			bit_count <= 0;
			clk_count <= 0;
			active <= 0;
			busy <= 0;
			avail <= 0;
	  end else if (start && !active) begin
			active <= 1;
			busy <= 1;
			avail <= 0;
			cs <= 0;
			shift_reg <= data_in;
			bit_count <= 8;
			p <= 0;
	  end else if (active) begin                                        // active inicia la comunicacion, transmision en curso	
			if (clk_count < div_factor - 1) begin                      // divisor del clk para obtener sclk
				 clk_count <= clk_count + 1;
			end else begin
				 clk_count <= 0;
				 sclk <= !sclk;

				 if (~sclk) begin                                       // flanco de subida de sclk se envia el bit mas significativo de shift_reg por mosi TRANSMITE
						mosi <= shift_reg[7];
						p <= ~p;
				 end else begin                                        // flanco de bajada de sclk 
					  if (bit_count > 0) begin
							bit_count <= bit_count - 1;
							shift_reg <= {shift_reg[6:0], miso};      		 //concatena a shift_reg, los ultimos 7 bits de shift_reg le agrega al final el bit de miso, bit mas reciente resivido por el esclavo
					  end else begin
							data_out <= shift_reg;
							cs <= 1;
							active <= 0;
							busy <= 0;
							avail <= 1;
					  end
				 end
			end
	  end
	end
endmodule

spi_testbench.v
`timescale 1ns / 1ps
`include "spi_master.v"

module spi_testbench;

    // Inputs
    reg clk;
    reg reset;
    reg [7:0] data_in;
    reg start;
    wire mosi;
    reg [15:0] div_factor;

    // Outputs
    reg miso;
    wire sclk;
    wire cs;
    wire [7:0] data_out;
    wire busy;
    wire avail;

    spi_master uut (
        .clk(clk),
        .reset(reset),
        .data_in(data_in),
        .start(start),
        .div_factor(div_factor),
        .miso(miso),
        .mosi(mosi),
        .sclk(sclk),
        .cs(cs),
        .data_out(data_out),
        .busy(busy),
        .avail(avail)
    );

    initial begin
        clk = 0;
        forever #1 clk = ~clk; // 50MHz
    end

    initial begin
        reset = 1;
        start = 0;
        miso = 0;
        div_factor = 8;  // Divisor de frecuencia para el reloj SPI
        data_in = 8'hA3;  // Data to send
        #5; 
        reset = 0;
        #5;

        // Iniciar transmisión
        start = 1;
        #5;
        start = 0;

        // Simulación de respuesta del esclavo
        forever begin
            if (sclk == 1 && cs == 0) begin
                miso <= ~mosi;  // Simular que el esclavo envía datos invertidos
            end
            #5;  // Esperar medio ciclo de reloj
        end
    end
	 initial begin: TEST_CASE
     $dumpfile("spi_testbench.vcd");
     $dumpvars(-1, uut);
     #(500) $finish;
   end


endmodule

spi_testbench.vcd
$date
	Tue Feb 25 17:59:32 2025
$end
$version
	Icarus Verilog
$end
$timescale
	1ps
$end
$scope module spi_testbench $end
$scope module uut $end
$var wire 1 ! clk $end
$var wire 8 " data_in [7:0] $end
$var wire 16 # div_factor [15:0] $end
$var wire 1 $ miso $end
$var wire 1 % reset $end
$var wire 1 & start $end
$var reg 1 ' active $end
$var reg 1 ( avail $end
$var reg 4 ) bit_count [3:0] $end
$var reg 1 * busy $end
$var reg 16 + clk_count [15:0] $end
$var reg 1 , cs $end
$var reg 8 - data_out [7:0] $end
$var reg 1 . mosi $end
$var reg 1 / p $end
$var reg 1 0 sclk $end
$var reg 8 1 shift_reg [7:0] $end
$upscope $end
$upscope $end
$enddefinitions $end
$comment Show the parameter values. $end
$dumpall
$end
#0
$dumpvars
b0 1
00
x/
x.
bx -
1,
b0 +
0*
b0 )
0(
0'
0&
1%
0$
b1000 #
b10100011 "
0!
$end
#1000
1!
#2000
0!
#3000
1!
#4000
0!
#5000
1!
0%
#6000
0!
#7000
1!
#8000
0!
#9000
1!
#10000
0!
1&
#11000
0/
b1000 )
b10100011 1
0,
1*
1'
1!
#12000
0!
#13000
b1 +
1!
#14000
0!
#15000
b10 +
1!
0&
#16000
0!
#17000
b11 +
1!
#18000
0!
#19000
b100 +
1!
#20000
0!
#21000
b101 +
1!
#22000
0!
#23000
b110 +
1!
#24000
0!
#25000
b111 +
1!
#26000
0!
#27000
1/
1.
10
b0 +
1!
#28000
0!
#29000
b1 +
1!
#30000
0!
#31000
b10 +
1!
#32000
0!
#33000
b11 +
1!
#34000
0!
#35000
b100 +
1!
#36000
0!
#37000
b101 +
1!
#38000
0!
#39000
b110 +
1!
#40000
0!
#41000
b111 +
1!
#42000
0!
#43000
b1000110 1
b111 )
00
b0 +
1!
#44000
0!
#45000
b1 +
1!
#46000
0!
#47000
b10 +
1!
#48000
0!
#49000
b11 +
1!
#50000
0!
#51000
b100 +
1!
#52000
0!
#53000
b101 +
1!
#54000
0!
#55000
b110 +
1!
#56000
0!
#57000
b111 +
1!
#58000
0!
#59000
0/
0.
10
b0 +
1!
#60000
1$
0!
#61000
b1 +
1!
#62000
0!
#63000
b10 +
1!
#64000
0!
#65000
b11 +
1!
#66000
0!
#67000
b100 +
1!
#68000
0!
#69000
b101 +
1!
#70000
0!
#71000
b110 +
1!
#72000
0!
#73000
b111 +
1!
#74000
0!
#75000
b10001101 1
b110 )
00
b0 +
1!
#76000
0!
#77000
b1 +
1!
#78000
0!
#79000
b10 +
1!
#80000
0!
#81000
b11 +
1!
#82000
0!
#83000
b100 +
1!
#84000
0!
#85000
b101 +
1!
#86000
0!
#87000
b110 +
1!
#88000
0!
#89000
b111 +
1!
#90000
0!
#91000
1/
1.
10
b0 +
1!
#92000
0!
#93000
b1 +
1!
#94000
0!
#95000
b10 +
0$
1!
#96000
0!
#97000
b11 +
1!
#98000
0!
#99000
b100 +
1!
#100000
0!
#101000
b101 +
1!
#102000
0!
#103000
b110 +
1!
#104000
0!
#105000
b111 +
1!
#106000
0!
#107000
b11010 1
b101 )
00
b0 +
1!
#108000
0!
#109000
b1 +
1!
#110000
0!
#111000
b10 +
1!
#112000
0!
#113000
b11 +
1!
#114000
0!
#115000
b100 +
1!
#116000
0!
#117000
b101 +
1!
#118000
0!
#119000
b110 +
1!
#120000
0!
#121000
b111 +
1!
#122000
0!
#123000
0/
0.
10
b0 +
1!
#124000
0!
#125000
b1 +
1$
1!
#126000
0!
#127000
b10 +
1!
#128000
0!
#129000
b11 +
1!
#130000
0!
#131000
b100 +
1!
#132000
0!
#133000
b101 +
1!
#134000
0!
#135000
b110 +
1!
#136000
0!
#137000
b111 +
1!
#138000
0!
#139000
b110101 1
b100 )
00
b0 +
1!
#140000
0!
#141000
b1 +
1!
#142000
0!
#143000
b10 +
1!
#144000
0!
#145000
b11 +
1!
#146000
0!
#147000
b100 +
1!
#148000
0!
#149000
b101 +
1!
#150000
0!
#151000
b110 +
1!
#152000
0!
#153000
b111 +
1!
#154000
0!
#155000
1/
10
b0 +
1!
#156000
0!
#157000
b1 +
1!
#158000
0!
#159000
b10 +
1!
#160000
0!
#161000
b11 +
1!
#162000
0!
#163000
b100 +
1!
#164000
0!
#165000
b101 +
1!
#166000
0!
#167000
b110 +
1!
#168000
0!
#169000
b111 +
1!
#170000
0!
#171000
b1101011 1
b11 )
00
b0 +
1!
#172000
0!
#173000
b1 +
1!
#174000
0!
#175000
b10 +
1!
#176000
0!
#177000
b11 +
1!
#178000
0!
#179000
b100 +
1!
#180000
0!
#181000
b101 +
1!
#182000
0!
#183000
b110 +
1!
#184000
0!
#185000
b111 +
1!
#186000
0!
#187000
0/
10
b0 +
1!
#188000
0!
#189000
b1 +
1!
#190000
0!
#191000
b10 +
1!
#192000
0!
#193000
b11 +
1!
#194000
0!
#195000
b100 +
1!
#196000
0!
#197000
b101 +
1!
#198000
0!
#199000
b110 +
1!
#200000
0!
#201000
b111 +
1!
#202000
0!
#203000
b11010111 1
b10 )
00
b0 +
1!
#204000
0!
#205000
b1 +
1!
#206000
0!
#207000
b10 +
1!
#208000
0!
#209000
b11 +
1!
#210000
0!
#211000
b100 +
1!
#212000
0!
#213000
b101 +
1!
#214000
0!
#215000
b110 +
1!
#216000
0!
#217000
b111 +
1!
#218000
0!
#219000
1/
1.
10
b0 +
1!
#220000
0$
0!
#221000
b1 +
1!
#222000
0!
#223000
b10 +
1!
#224000
0!
#225000
b11 +
1!
#226000
0!
#227000
b100 +
1!
#228000
0!
#229000
b101 +
1!
#230000
0!
#231000
b110 +
1!
#232000
0!
#233000
b111 +
1!
#234000
0!
#235000
b10101110 1
b1 )
00
b0 +
1!
#236000
0!
#237000
b1 +
1!
#238000
0!
#239000
b10 +
1!
#240000
0!
#241000
b11 +
1!
#242000
0!
#243000
b100 +
1!
#244000
0!
#245000
b101 +
1!
#246000
0!
#247000
b110 +
1!
#248000
0!
#249000
b111 +
1!
#250000
0!
#251000
0/
10
b0 +
1!
#252000
0!
#253000
b1 +
1!
#254000
0!
#255000
b10 +
1!
#256000
0!
#257000
b11 +
1!
#258000
0!
#259000
b100 +
1!
#260000
0!
#261000
b101 +
1!
#262000
0!
#263000
b110 +
1!
#264000
0!
#265000
b111 +
1!
#266000
0!
#267000
b1011100 1
b0 )
00
b0 +
1!
#268000
0!
#269000
b1 +
1!
#270000
0!
#271000
b10 +
1!
#272000
0!
#273000
b11 +
1!
#274000
0!
#275000
b100 +
1!
#276000
0!
#277000
b101 +
1!
#278000
0!
#279000
b110 +
1!
#280000
0!
#281000
b111 +
1!
#282000
0!
#283000
1/
0.
10
b0 +
1!
#284000
0!
#285000
b1 +
1$
1!
#286000
0!
#287000
b10 +
1!
#288000
0!
#289000
b11 +
1!
#290000
0!
#291000
b100 +
1!
#292000
0!
#293000
b101 +
1!
#294000
0!
#295000
b110 +
1!
#296000
0!
#297000
b111 +
1!
#298000
0!
#299000
1(
0*
0'
1,
b1011100 -
00
b0 +
1!
